libfinance/__init__.py
libfinance/client.py
libfinance/api/__init__.py
libfinance/api/calendar.py
libfinance/api/concept_components.py
libfinance/api/get_price.py
libfinance/api/index_components.py
libfinance/api/instrument.py
libfinance/utils/__init__.py
libfinance/utils/datetime_func.py
libfinance/utils/decorators.py
libfinance/utils/utils.py
libfinance/utils/validators.py
libfinance-0.0.6.dist-info/METADATA
libfinance-0.0.6.dist-info/WHEEL
libfinance-0.0.6.dist-info/top_level.txt
libfinance-0.0.6.dist-info/RECORD
