Metadata-Version: 2.4
Name: libfinance
Version: 0.0.6
Summary: libfinance is a modern finance API
Requires-Dist: lz4
Requires-Dist: msgpack
Requires-Dist: pandas
